nitypes/__init__.py
nitypes/_arguments.py
nitypes/_exceptions.py
nitypes/_numpy.py
nitypes/_numpy1x.py
nitypes/_version.py
nitypes/bintime/__init__.py
nitypes/bintime/_datetime.py
nitypes/bintime/_datetime_array.py
nitypes/bintime/_dtypes.py
nitypes/bintime/_time_value_tuple.py
nitypes/bintime/_timedelta.py
nitypes/bintime/_timedelta_array.py
nitypes/complex/__init__.py
nitypes/complex/_conversion.py
nitypes/complex/_dtypes.py
nitypes/py.typed
nitypes/scalar.py
nitypes/time/__init__.py
nitypes/time/_conversion.py
nitypes/time/_types.py
nitypes/time/typing.py
nitypes/vector.py
nitypes/waveform/__init__.py
nitypes/waveform/_analog.py
nitypes/waveform/_complex.py
nitypes/waveform/_digital/__init__.py
nitypes/waveform/_digital/_port.py
nitypes/waveform/_digital/_signal.py
nitypes/waveform/_digital/_signal_collection.py
nitypes/waveform/_digital/_state.py
nitypes/waveform/_digital/_waveform.py
nitypes/waveform/_exceptions.py
nitypes/waveform/_extended_properties.py
nitypes/waveform/_numeric.py
nitypes/waveform/_scaling/__init__.py
nitypes/waveform/_scaling/_base.py
nitypes/waveform/_scaling/_linear.py
nitypes/waveform/_scaling/_none.py
nitypes/waveform/_spectrum.py
nitypes/waveform/_timing/__init__.py
nitypes/waveform/_timing/_sample_interval/__init__.py
nitypes/waveform/_timing/_sample_interval/_base.py
nitypes/waveform/_timing/_sample_interval/_irregular.py
nitypes/waveform/_timing/_sample_interval/_mode.py
nitypes/waveform/_timing/_sample_interval/_none.py
nitypes/waveform/_timing/_sample_interval/_regular.py
nitypes/waveform/_timing/_timing.py
nitypes/waveform/_types.py
nitypes/waveform/_warnings.py
nitypes/waveform/errors.py
nitypes/waveform/typing.py
nitypes/waveform/warnings.py
nitypes-1.0.0.dist-info/LICENSE
nitypes-1.0.0.dist-info/METADATA
nitypes-1.0.0.dist-info/WHEEL
nitypes-1.0.0.dist-info/RECORD
