Metadata-Version: 2.3
Name: nitypes
Version: 1.0.0
Summary: Data types for NI Python APIs
License: MIT
Keywords: nitypes
Author: NI
Author-email: opensource@ni.com
Maintainer: Brad Keryan
Maintainer-email: brad.keryan@ni.com
Requires-Python: >=3.9,<4.0
Classifier: Development Status :: 5 - Production/Stable
Classifier: Intended Audience :: Developers
Classifier: Intended Audience :: Manufacturing
Classifier: Intended Audience :: Science/Research
Classifier: License :: OSI Approved :: MIT License
Classifier: Operating System :: Microsoft :: Windows
Classifier: Operating System :: POSIX
Classifier: Programming Language :: Python :: 3
Classifier: Programming Language :: Python :: 3.9
Classifier: Programming Language :: Python :: 3.10
Classifier: Programming Language :: Python :: 3.11
Classifier: Programming Language :: Python :: 3.12
Classifier: Programming Language :: Python :: 3.13
Classifier: Programming Language :: Python :: Implementation :: CPython
Classifier: Programming Language :: Python :: Implementation :: PyPy
Requires-Dist: hightime (>=0.2.2)
Requires-Dist: numpy (>=1.22) ; python_version >= "3.9" and python_version < "3.13"
Requires-Dist: numpy (>=2.1) ; python_version >= "3.13" and python_version < "4.0"
Requires-Dist: typing-extensions (>=4.13.2)
Project-URL: Documentation, https://nitypes.readthedocs.io/
Project-URL: Repository, https://github.com/ni/nitypes-python
